ArithNBold/BoldArith.py
ArithNBold/__init__.py
ArithNBold-1.1.dist-info/METADATA
ArithNBold-1.1.dist-info/WHEEL
ArithNBold-1.1.dist-info/top_level.txt
ArithNBold-1.1.dist-info/RECORD
