Metadata-Version: 2.1
Name: ArithNBold
Version: 1.1
Summary: Contains 5 arithmetic functions for addition, subtraction, multiplication, division, and factorial
Home-page: UNKNOWN
Author: NBold
Author-email: UNKNOWN
License: UNKNOWN
Platform: UNKNOWN
